telecom/__init__.py
telecom/admin.py
telecom/apps.py
telecom/models.py
telecom/serializers.py
telecom/tests.py
telecom/urls.py
telecom/utils.py
telecom/views.py
telecom/migrations/__init__.py
django_message-1.3.dist-info/LICENSE
django_message-1.3.dist-info/METADATA
django_message-1.3.dist-info/WHEEL
django_message-1.3.dist-info/top_level.txt
django_message-1.3.dist-info/RECORD
